python_playground/__init__.py
python_playground-0.1.0.dist-info/WHEEL
python_playground-0.1.0.dist-info/METADATA
python_playground-0.1.0.dist-info/RECORD
