Metadata-Version: 2.1
Name: python-playground
Version: 0.1.0
Summary: 
Author: jerilcj3
Author-email: jerilcj3@gmail.com
Requires-Python: >=3.6,<4.0
Classifier: Programming Language :: Python :: 3
Classifier: Programming Language :: Python :: 3.6
Classifier: Programming Language :: Python :: 3.7
Classifier: Programming Language :: Python :: 3.8
Requires-Dist: requests (>=2.23.0,<3.0.0)
